reprint/__init__.py
reprint/reprint.py
reprint-0.5.1.dist-info/DESCRIPTION.rst
reprint-0.5.1.dist-info/METADATA
reprint-0.5.1.dist-info/RECORD
reprint-0.5.1.dist-info/WHEEL
reprint-0.5.1.dist-info/metadata.json
reprint-0.5.1.dist-info/top_level.txt
